pooch/__init__.py
pooch/_version.py
pooch/core.py
pooch/downloaders.py
pooch/hashes.py
pooch/processors.py
pooch/utils.py
pooch/tests/__init__.py
pooch/tests/test_core.py
pooch/tests/test_downloaders.py
pooch/tests/test_hashes.py
pooch/tests/test_integration.py
pooch/tests/test_processors.py
pooch/tests/test_utils.py
pooch/tests/test_version.py
pooch/tests/utils.py
pooch/tests/data/large-data.txt
pooch/tests/data/registry-custom-url.txt
pooch/tests/data/registry-invalid.txt
pooch/tests/data/registry-spaces.txt
pooch/tests/data/registry.txt
pooch/tests/data/registry_comments.txt
pooch/tests/data/store.tar.gz
pooch/tests/data/store.zip
pooch/tests/data/tiny-data.tar.gz
pooch/tests/data/tiny-data.txt
pooch/tests/data/tiny-data.txt.bz2
pooch/tests/data/tiny-data.txt.gz
pooch/tests/data/tiny-data.txt.xz
pooch/tests/data/tiny-data.zip
pooch/tests/data/store/tiny-data.txt
pooch/tests/data/store/subdir/tiny-data.txt
pooch-1.8.1.dist-info/LICENSE.txt
pooch-1.8.1.dist-info/METADATA
pooch-1.8.1.dist-info/WHEEL
pooch-1.8.1.dist-info/top_level.txt
pooch-1.8.1.dist-info/zip-safe
pooch-1.8.1.dist-info/RECORD
