Metadata-Version: 2.1
Name: pooch
Version: 1.8.1
Summary: "Pooch manages your Python library's sample data files: it automatically downloads and stores them in a local directory, with support for versioning and corruption checks."
Home-page: https://github.com/fatiando/pooch
Author: The Pooch Developers
Author-email: fatiandoaterra@protonmail.com
Maintainer: "Leonardo Uieda"
Maintainer-email: leouieda@gmail.com
License: BSD 3-Clause License
Project-URL: Documentation, https://www.fatiando.org/pooch
Project-URL: Release Notes, https://github.com/fatiando/pooch/releases
Project-URL: Bug Tracker, https://github.com/fatiando/pooch/issues
Project-URL: Source Code, https://github.com/fatiando/pooch
Keywords: data,download,caching,http
Platform: any
Classifier: Development Status :: 5 - Production/Stable
Classifier: Intended Audience :: Science/Research
Classifier: Intended Audience :: Developers
Classifier: Intended Audience :: Education
Classifier: License :: OSI Approved :: BSD License
Classifier: Natural Language :: English
Classifier: Operating System :: OS Independent
Classifier: Topic :: Scientific/Engineering
Classifier: Topic :: Software Development :: Libraries
Classifier: Programming Language :: Python :: 3 :: Only
Classifier: Programming Language :: Python :: 3.7
Classifier: Programming Language :: Python :: 3.8
Classifier: Programming Language :: Python :: 3.9
Classifier: Programming Language :: Python :: 3.10
Classifier: Programming Language :: Python :: 3.11
Requires-Python: >=3.7
License-File: LICENSE.txt
Requires-Dist: platformdirs>=2.5.0
Requires-Dist: packaging>=20.0
Requires-Dist: requests>=2.19.0
Provides-Extra: progress
Requires-Dist: tqdm<5.0.0,>=4.41.0; extra == "progress"
Provides-Extra: sftp
Requires-Dist: paramiko>=2.7.0; extra == "sftp"
Provides-Extra: xxhash
Requires-Dist: xxhash>=1.4.3; extra == "xxhash"
